wordleanswer/__init__.py
wordleanswer-1.0.1.dist-info/LICENSE
wordleanswer-1.0.1.dist-info/METADATA
wordleanswer-1.0.1.dist-info/WHEEL
wordleanswer-1.0.1.dist-info/top_level.txt
wordleanswer-1.0.1.dist-info/RECORD
