Metadata-Version: 2.1
Name: wordleanswer
Version: 1.0.1
Summary: A package to get the Wordle answers
Home-page: https://github.com/sensoorr/wordleanswer
Author: Sensor
Author-email: sensoorr@hotmail.com
License: UNKNOWN
Project-URL: Bug Tracker, https://github.com/sensoorr/wordleanswer/issues
Platform: UNKNOWN
Classifier: Programming Language :: Python :: 3
Classifier: License :: OSI Approved :: MIT License
Classifier: Operating System :: OS Independent
Requires-Python: >=3.6
License-File: LICENSE
